main.py
git_summarise-0.1.2.dist-info/METADATA
git_summarise-0.1.2.dist-info/WHEEL
git_summarise-0.1.2.dist-info/entry_points.txt
git_summarise-0.1.2.dist-info/top_level.txt
git_summarise-0.1.2.dist-info/RECORD
